Metadata-Version: 2.1
Name: django-fav
Version: 0.3
Summary: A simple reusable app for django that makes it easy to deal with faving and unfaving any object from any application.
Home-page: https://vied12.github.io
Author: Edouard Richard
Author-email: edou4rd@gmail.com
License: BSD License
Platform: UNKNOWN
Classifier: Environment :: Web Environment
Classifier: Framework :: Django
Classifier: Framework :: Django :: 1.11
Classifier: Intended Audience :: Developers
Classifier: License :: OSI Approved :: BSD License
Classifier: Operating System :: OS Independent
Classifier: Programming Language :: Python :: 3
Classifier: Programming Language :: Python :: 3.4
Classifier: Programming Language :: Python :: 3.5
Classifier: Programming Language :: Python :: 3.6
